django_gazing_select_widget/__init__.py
django_gazing_select_widget/admin.py
django_gazing_select_widget/apps.py
django_gazing_select_widget/models.py
django_gazing_select_widget/tests.py
django_gazing_select_widget/views.py
django_gazing_select_widget/widgets.py
django_gazing_select_widget/migrations/__init__.py
django_gazing_select_widget/static/django-gazing-select-widget/js/django-gazing-select-widget.js
django_gazing_select_widget/templates/django-gazing-select-widget/django-gazing-select-widget.html
django_gazing_select_widget-0.1.2.dist-info/LICENSE
django_gazing_select_widget-0.1.2.dist-info/METADATA
django_gazing_select_widget-0.1.2.dist-info/WHEEL
django_gazing_select_widget-0.1.2.dist-info/top_level.txt
django_gazing_select_widget-0.1.2.dist-info/RECORD
